{
	"base_price": 7500000,
	"parents": ["qc_reduce_maintenance1","qc_reduce_cost2"],
	"parent_requirement_type":["and",0],
	"upgrade_time":20000,
	"base_success_probability":1,
	"name":"qc_reduce_maintenance2",
	"start_unlocked":false,
	"auto_activate":true,
	"employee_type":"rnd",
	"buy_requirements":
	{
		"type":"none"
	},
	"effects":[
		{
			"effect_type":"var",
			"effect_requirements":{"type":"none"},
			"period":0,
			"variable":"production_methods.quantumcreme_alpha.maintenance_cost",
			"value":0.9,
			"op":"mult",
		},
		{
			"effect_type":"var",
			"effect_requirements":{"type":"none"},
			"period":0,
			"variable":"production_methods.quantumcreme_beta.maintenance_cost",
			"value":0.9,
			"op":"mult",
		},
		{
			"effect_type":"var",
			"effect_requirements":{"type":"none"},
			"period":0,
			"variable":"production_methods.quantumcreme_gamma.maintenance_cost",
			"value":0.9,
			"op":"mult",
		},
		{
			"effect_type":"var",
			"effect_requirements":{"type":"none"},
			"period":0,
			"variable":"production_methods.quantumcreme_delta.maintenance_cost",
			"value":0.8,
			"op":"mult",
		},
		{
			"effect_type":"var",
			"effect_requirements":{"type":"none"},
			"period":0,
			"variable":"production_methods.quantumcreme_omega.maintenance_cost",
			"value":0.8,
			"op":"mult",
		}
	]
}
